coreason_archive/__init__.py
coreason_archive/archive.py
coreason_archive/extractors.py
coreason_archive/federation.py
coreason_archive/graph_store.py
coreason_archive/interfaces.py
coreason_archive/main.py
coreason_archive/matchmaker.py
coreason_archive/models.py
coreason_archive/relocation.py
coreason_archive/server.py
coreason_archive/temporal.py
coreason_archive/utils/__init__.py
coreason_archive/utils/logger.py
coreason_archive/utils/runners.py
coreason_archive/utils/stubs.py
coreason_archive/vector_store.py
coreason_archive-0.6.0.dist-info/METADATA
coreason_archive-0.6.0.dist-info/WHEEL
coreason_archive-0.6.0.dist-info/licenses/LICENSE
coreason_archive-0.6.0.dist-info/licenses/NOTICE
coreason_archive-0.6.0.dist-info/RECORD
