Metadata-Version: 2.4
Name: coreason_archive
Version: 0.6.0
Summary: persistence layer for Cognitive State across the CoReason ecosystem
License: # The Prosperity Public License 3.0.0
License-File: LICENSE
License-File: NOTICE
Author: Gowtham A Rao
Author-email: gowtham.rao@coreason.ai
Requires-Python: >=3.11
Classifier: License :: Other/Proprietary License
Classifier: Programming Language :: Python :: 3.12
Classifier: Operating System :: OS Independent
Requires-Dist: anyio (>=4.12.1,<5.0.0)
Requires-Dist: coreason-identity
Requires-Dist: fastapi (>=0.110.0,<0.111.0)
Requires-Dist: httpx (>=0.28.1,<0.29.0)
Requires-Dist: loguru (>=0.7.2,<0.8.0)
Requires-Dist: networkx (>=3.4,<4.0)
Requires-Dist: numpy (>=1.26.0)
Requires-Dist: pydantic (>=2.7.0,<3.0.0)
Requires-Dist: uvicorn[standard] (>=0.29.0,<0.30.0)
Project-URL: Documentation, https://github.com/CoReason-AI/coreason-archive
Project-URL: Homepage, https://github.com/CoReason-AI/coreason-archive
Project-URL: Repository, https://github.com/CoReason-AI/coreason-archive
